ZuishouNvshengHuanyingde30daHuati/README.md
ZuishouNvshengHuanyingde30daHuati/__init__.py
ZuishouNvshengHuanyingde30daHuati/__main__.py
ZuishouNvshengHuanyingde30daHuati/file.epub
ZuishouNvshengHuanyingde30daHuati/index.html
ZuishouNvshengHuanyingde30daHuati/css/__init__.py
ZuishouNvshengHuanyingde30daHuati/css/annotations.css
ZuishouNvshengHuanyingde30daHuati/css/main.css
ZuishouNvshengHuanyingde30daHuati/css/normalize.css
ZuishouNvshengHuanyingde30daHuati/css/popup.css
ZuishouNvshengHuanyingde30daHuati/font/__init__.py
ZuishouNvshengHuanyingde30daHuati/font/fontello.eot
ZuishouNvshengHuanyingde30daHuati/font/fontello.svg
ZuishouNvshengHuanyingde30daHuati/font/fontello.ttf
ZuishouNvshengHuanyingde30daHuati/font/fontello.woff
ZuishouNvshengHuanyingde30daHuati/img/__init__.py
ZuishouNvshengHuanyingde30daHuati/img/annotator-glyph-sprite.png
ZuishouNvshengHuanyingde30daHuati/img/annotator-icon-sprite.png
ZuishouNvshengHuanyingde30daHuati/img/apple-touch-icon.png
ZuishouNvshengHuanyingde30daHuati/img/cancelfullscreen.png
ZuishouNvshengHuanyingde30daHuati/img/close.png
ZuishouNvshengHuanyingde30daHuati/img/fullscreen.png
ZuishouNvshengHuanyingde30daHuati/img/loader.gif
ZuishouNvshengHuanyingde30daHuati/img/menu-icon.png
ZuishouNvshengHuanyingde30daHuati/img/save.png
ZuishouNvshengHuanyingde30daHuati/img/saved.png
ZuishouNvshengHuanyingde30daHuati/img/settings-s.png
ZuishouNvshengHuanyingde30daHuati/img/settings.png
ZuishouNvshengHuanyingde30daHuati/img/star.png
ZuishouNvshengHuanyingde30daHuati/js/__init__.py
ZuishouNvshengHuanyingde30daHuati/js/epub.js
ZuishouNvshengHuanyingde30daHuati/js/epub.min.js
ZuishouNvshengHuanyingde30daHuati/js/epub.min.map
ZuishouNvshengHuanyingde30daHuati/js/hooks.min.js
ZuishouNvshengHuanyingde30daHuati/js/hooks.min.map
ZuishouNvshengHuanyingde30daHuati/js/reader.js
ZuishouNvshengHuanyingde30daHuati/js/reader.js.map
ZuishouNvshengHuanyingde30daHuati/js/reader.min.js
ZuishouNvshengHuanyingde30daHuati/js/reader.min.map
zuishou_nvsheng_huanyingde_30da_huati-2022.10.11.0.dist-info/METADATA
zuishou_nvsheng_huanyingde_30da_huati-2022.10.11.0.dist-info/WHEEL
zuishou_nvsheng_huanyingde_30da_huati-2022.10.11.0.dist-info/entry_points.txt
zuishou_nvsheng_huanyingde_30da_huati-2022.10.11.0.dist-info/top_level.txt
zuishou_nvsheng_huanyingde_30da_huati-2022.10.11.0.dist-info/RECORD
